code_timer/__init__.py
code_timer/timer.py
code_timer-2.0.0.dist-info/LICENSE
code_timer-2.0.0.dist-info/METADATA
code_timer-2.0.0.dist-info/WHEEL
code_timer-2.0.0.dist-info/top_level.txt
code_timer-2.0.0.dist-info/RECORD
