Metadata-Version: 2.1
Name: code-timer
Version: 2.0.0
Summary: Custom timer for your Python coding pleasure
Home-page: https://github.com/StephenGemin/code_timer
Author: Stephen Gemin
Author-email: s.gemin88@gmail.com
License: MIT License
Download-URL: https://github.com/StephenGemin/code_timer/
Keywords: decorator,decorators,code timer,timing,code timing,context manager,profiling
Platform: UNKNOWN
Classifier: Development Status :: 3 - Alpha
Classifier: Intended Audience :: Developers
Classifier: Topic :: Software Development :: Debuggers
Classifier: License :: OSI Approved :: MIT License
Classifier: Programming Language :: Python :: 3.6
Classifier: Programming Language :: Python :: 3.7
Classifier: Programming Language :: Python :: 3.8
Classifier: Programming Language :: Python :: 3.9
License-File: LICENSE
Provides-Extra: dev
Requires-Dist: pytest ; extra == 'dev'
Requires-Dist: pytest-pep8 ; extra == 'dev'
Requires-Dist: pytest-cov ; extra == 'dev'
